bd_fileorganizer/__init__.py
bd_fileorganizer/cli.py
bd_fileorganizer/organizer.py
bd_fileorganizer-0.0.7.dist-info/METADATA
bd_fileorganizer-0.0.7.dist-info/WHEEL
bd_fileorganizer-0.0.7.dist-info/entry_points.txt
bd_fileorganizer-0.0.7.dist-info/licenses/LICENSE
bd_fileorganizer-0.0.7.dist-info/RECORD
