Metadata-Version: 2.4
Name: bd_fileorganizer
Version: 0.0.7
Summary: Organize files in folders by type
Author-email: Bhuvan Boddu <bhuvanboddu08@gmail.com>, Devaraj Agulla <devaagulla770@gmail.com>
License-File: LICENSE
Classifier: License :: OSI Approved :: GNU General Public License v3 (GPLv3)
Classifier: Operating System :: OS Independent
Classifier: Programming Language :: Python :: 3
Requires-Python: >=3.8
